{
    "compilerOptions": {
        "incremental": true,
        "tsBuildInfoFile": "./tsconfig.tsbuildinfo",
        "target": "ES2024",
        "module": "ESNext",
        "lib": ["ES2024", "DOM"],
        "moduleResolution": "bundler",
        "strict": true,
        "esModuleInterop": true,
        "forceConsistentCasingInFileNames": true,
        "skipLibCheck": true,
        "resolveJsonModule": true,
        "allowImportingTsExtensions": true,
        "noUncheckedIndexedAccess": true,
        "isolatedModules": true,
        "useDefineForClassFields": true,
        "verbatimModuleSyntax": true,
        "noFallthroughCasesInSwitch": true,
        "noUnusedLocals": true,
        "noUnusedParameters": true,
        "noEmit": true
    }
}
